rushdata/__init__.py
rushdata/data.py
rushdata/identifier.py
rushdata/utils.py
rushdata/resource/__init__.py
rushdata/resource/data.py
rushdata-0.1.1.dist-info/licenses/LICENSE.txt
scripts/build.py
scripts/install.py
test/main.py
test/assets/texture/1.py
test/assets/uil/2.py
rushdata-0.1.1.dist-info/METADATA
rushdata-0.1.1.dist-info/WHEEL
rushdata-0.1.1.dist-info/top_level.txt
rushdata-0.1.1.dist-info/RECORD
