Metadata-Version: 2.4
Name: rushdata
Version: 0.1.1
Summary: python data
Author-email: ndrzy <dandan0019@outlook.com>
License: MIT
Project-URL: Homepage, https://github.com/meatdumplings0019/rushdata
Requires-Python: >=3.10
License-File: LICENSE.txt
Requires-Dist: colorama
Requires-Dist: rushlib
Dynamic: license-file
